gimmie/__init__.py
gimmie/main.py
gimmie-0.1.0.dist-info/METADATA
gimmie-0.1.0.dist-info/WHEEL
gimmie-0.1.0.dist-info/entry_points.txt
gimmie-0.1.0.dist-info/licenses/LICENSE
gimmie-0.1.0.dist-info/RECORD
